Metadata-Version: 2.1
Name: backend-workshop-microservices-common
Version: 1.0
Summary: Qustodio backend_workshop_microservices common repo
Home-page: https://github.com/qustodio/backend_workshop_microservices
Author: Qustodio developers
Author-email: info@qustodio.com
License: MIT
Platform: UNKNOWN
Classifier: Programming Language :: Python :: 3
Classifier: Programming Language :: Python :: 3.8
Requires-Python: >=3.6
